code_assistant/__init__.py
code_assistant/app.py
code_assistant/assistants.py
code_assistant/code_assistant.py
code_assistant/main.py
code_assistant/constants/__init__.py
code_assistant/constants/config.py
code_assistant/constants/css_text.py
code_assistant/constants/post_message_listener_src.py
code_assistant/constants/scroll_script_src.py
code_assistant/constants/starter_app.py
code_assistant/constants/context/__init__.py
code_assistant/constants/context/big_fasthtml_context.py
code_assistant/constants/context/fasthtml_llms_txt.py
code_assistant/constants/context/htmx_context.py
code_assistant/constants/context/small_fasthtml_context.py
code_assistant/generated_apps/calculator_app/app.py
code_assistant/generated_apps/fast_game/app.py
code_assistant/generated_apps/fasthtml_k8s_app/app.py
code_assistant/generated_apps/fasthtml_mortgage_calculator/app.py
code_assistant/generated_apps/graphing_calculator/app.py
code_assistant/generated_apps/minecraft_clone/app.py
code_assistant/generated_apps/photo_book_app/app.py
code_assistant/generated_apps/riddle_generator/app.py
code_assistant/generated_apps/roll_dice_app/app.py
code_assistant/generated_apps/scavenger_hunt_app/app.py
code_assistant/generated_apps/sudoku_app/app.py
code_assistant/generated_apps/tick_tack_toe/app.py
code_assistant/generated_apps/trivia_app/app.py
code_assistant/routes/chat_message.py
code_assistant/routes/code.py
code_assistant/routes/context.py
code_assistant/routes/edit.py
code_assistant/routes/file_rt.py
code_assistant/routes/fix_errors.py
code_assistant/routes/home.py
code_assistant/routes/preview.py
code_assistant/routes/set_keys.py
code_assistant/routes/update_provider.py
code_assistant/routes/upload.py
code_assistant/scripts/migrate_to_project_dirs.py
code_assistant/tests/__init__.py
code_assistant/tests/simple.py
code_assistant/tests/fixtures/500_error.py
code_assistant/tests/fixtures/500_error_requires_details_to_fix.py
code_assistant/tests/fixtures/Redirect_andRedirectResponse.py
code_assistant-0.1.1.dist-info/METADATA
code_assistant-0.1.1.dist-info/WHEEL
code_assistant-0.1.1.dist-info/entry_points.txt
code_assistant-0.1.1.dist-info/RECORD
