Metadata-Version: 2.3
Name: code-assistant
Version: 0.1.1
Summary: A FastHTML app that builds FastHTML apps
Author-email: phact <estevezsebastian@gmail.com>
Requires-Python: >=3.11
Requires-Dist: ast-grep-py>=0.26.3
Requires-Dist: astra-assistants>=2.1.0.27
Requires-Dist: python-fasthtml>=0.5.1
